{
  "appName": "Jira_Suite",
  "description": "Jira Cloud REST API v3 integration for issue management, project tracking, and team collaboration.",
  "domain": "project_management",
  "use_case": "Issue creation and search, project oversight, team collaboration, status tracking, and comment management.",
  "tier": "verified",
  "auth_type": "Basic",
  "header_key": "Authorization",
  "versions": [
    {
      "semver": "1.0.0",
      "tools": [
        "Jira_SearchIssues",
        "Jira_GetIssue",
        "Jira_CreateIssue",
        "Jira_UpdateIssue",
        "Jira_GetProject",
        "Jira_AddComment"
      ]
    }
  ]
}
