{
  "appName": "eBay_Marketplace_Suite",
  "description": "eBay Browse API v1 integration for marketplace research, product discovery, price analysis, and trend monitoring. Read-only access to item search, product details, item variations, visual search capabilities, and marketplace trending deals.",
  "domain": "marketplace",
  "use_case": "Item search and discovery, product price research, marketplace trend analysis, item detail retrieval, product variation exploration, visual search capabilities, and trending deal identification.",
  "tier": "verified",
  "auth_type": "Bearer Token",
  "header_key": "Authorization",
  "versions": [
    {
      "semver": "1.0.0",
      "tools": [
        "eBay_SearchItems",
        "eBay_GetItem",
        "eBay_GetItemsByGroup",
        "eBay_SearchByImage",
        "eBay_GetMarketplaceTrending"
      ]
    }
  ]
}
